MANIFEST.in
README.md
requirements.txt
setup.py
fourier_neural_operator/__init__.py
fourier_neural_operator/fourier_1d.py
fourier_neural_operator/fourier_2d.py
fourier_neural_operator/fourier_2d_factorized.py
fourier_neural_operator/fourier_2d_factorized_conditional.py
fourier_neural_operator/fourier_2d_factorized_conditional_v2.py
fourier_neural_operator/fourier_2d_factorized_conditional_v3.py
fourier_neural_operator/fourier_2d_factorized_v2.py
fourier_neural_operator/fourier_2d_time.py
fourier_neural_operator/fourier_3d.py
fourier_neural_operator/fourier_unet.py
fourier_neural_operator/fourier_unet_conditional.py
fourier_neural_operator/linear.py
fourier_neural_operator/lowrank_1d.py
fourier_neural_operator/lowrank_2d.py
fourier_neural_operator/lowrank_2d_time.py
fourier_neural_operator/lowrank_3d.py
fourier_neural_operator/utilities3.py
fourier_neural_operator.egg-info/PKG-INFO
fourier_neural_operator.egg-info/SOURCES.txt
fourier_neural_operator.egg-info/dependency_links.txt
fourier_neural_operator.egg-info/requires.txt
fourier_neural_operator.egg-info/top_level.txt
fourier_neural_operator/layers/__init__.py
fourier_neural_operator/layers/fourier_1d.py
fourier_neural_operator/layers/fourier_2d.py
fourier_neural_operator/layers/fourier_2d_factorized.py
fourier_neural_operator/layers/fourier_2d_factorized_v2.py
fourier_neural_operator/layers/fourier_2d_factorized_v3.py
fourier_neural_operator/layers/fourier_2d_time.py
fourier_neural_operator/layers/fourier_3d.py
fourier_neural_operator/layers/linear.py
fourier_neural_operator/layers/lowrank_1d.py
fourier_neural_operator/layers/lowrank_2d.py
fourier_neural_operator/layers/lowrank_2d_time.py
fourier_neural_operator/layers/lowrank_3d.py