Metadata-Version: 2.1
Name: fourier-neural-operator
Version: 0.17
Summary: Library and exemples to use the fourier neural operator
Home-page: https://github.com/Forbu/fourier_neural_operator
License: UNKNOWN
Platform: UNKNOWN
